gitlab_github_mirror_repo
