Metadata-Version: 2.1
Name: gitlab-github-mirror-repo
Version: 0.1.1
Summary: Script used to create repos on Gitlab and Github. Then create a push mirror link between them Gitlab -> Github.
Home-page: https://gitlab.com/gitlab-automation-toolkit/gitlab-github-mirror-repo
Author: Haseeb Majid
Author-email: hello@haseebmajid.dev
License: Apache License
Keywords: script,gitlab,github,mirror,automation
Platform: UNKNOWN
Classifier: Programming Language :: Python
Classifier: Intended Audience :: Developers
Classifier: Operating System :: OS Independent
Classifier: Topic :: Software Development :: Libraries :: Python Modules
Requires-Python: ~=3.6
